dllist/__init__.py
dllist/macos.py
dllist/py.typed
dllist/unix_like.py
dllist/windows.py
dllist-1.2.0.dist-info/LICENSE
dllist-1.2.0.dist-info/METADATA
dllist-1.2.0.dist-info/WHEEL
dllist-1.2.0.dist-info/top_level.txt
dllist-1.2.0.dist-info/RECORD
