Metadata-Version: 2.1
Name: dllist
Version: 1.2.0
Summary: List the shared libraries loaded by the current process.
Author-email: Brian Ward <bward@flatironinstitute.org>
License: BSD-3-Clause
Project-URL: Homepage, https://github.com/wardbrian/dllist
Project-URL: Bug Tracker, https://github.com/wardbrian/dllist/issues
Classifier: Programming Language :: Python :: 3
Classifier: Development Status :: 5 - Production/Stable
Classifier: License :: OSI Approved :: BSD License
Classifier: Topic :: System
Classifier: Topic :: Utilities
Requires-Python: >=3.8
License-File: LICENSE
Provides-Extra: test
Requires-Dist: pytest ; extra == 'test'
Requires-Dist: pytest-cov ; extra == 'test'
